comath/__init__.py
comath/_version.py
comath/array/__init__.py
comath/array/array.py
comath/func/__init__.py
comath/func/func.py
comath/metric/__init__.py
comath/metric/metric.py
comath/segment/__init__.py
comath/segment/segment.py
comath-0.0.7.dist-info/METADATA
comath-0.0.7.dist-info/RECORD
comath-0.0.7.dist-info/WHEEL
comath-0.0.7.dist-info/top_level.txt
tests/__init__.py
