Metadata-Version: 2.1
Name: comath
Version: 0.0.7
Summary: Math-related utility functions.
Home-page: https://github.com/shaypal5/comath
Author: Shay Palachy
Author-email: shaypal5@gmail.com
License: MIT
Keywords: python math array metric function segment
Platform: UNKNOWN
Classifier: Development Status :: 4 - Beta
Classifier: License :: OSI Approved :: MIT License
Classifier: Programming Language :: Python
Classifier: Programming Language :: Python :: 3.4
Classifier: Programming Language :: Python :: 3.5
Classifier: Programming Language :: Python :: 3.6
Classifier: Programming Language :: Python :: 3.7
Classifier: Topic :: Software Development :: Libraries
Classifier: Topic :: Software Development :: Libraries :: Python Modules
Classifier: Intended Audience :: Developers
Requires-Python: >=3.5
Provides-Extra: test
Provides-Extra: test
Requires-Dist: pytest; extra == 'test'
Requires-Dist: coverage; extra == 'test'
Requires-Dist: pytest-cov; extra == 'test'
Requires-Dist: collective.checkdocs; extra == 'test'
Requires-Dist: pygments; extra == 'test'
